LICENSE
README.md
setup.py
facebook_scraper_in/__init__.py
facebook_scraper_in.egg-info/PKG-INFO
facebook_scraper_in.egg-info/SOURCES.txt
facebook_scraper_in.egg-info/dependency_links.txt
facebook_scraper_in.egg-info/requires.txt
facebook_scraper_in.egg-info/top_level.txt